balmung/__init__.py
balmung/balmung.py
balmung-0.0.0.dist-info/LICENSE
balmung-0.0.0.dist-info/METADATA
balmung-0.0.0.dist-info/WHEEL
balmung-0.0.0.dist-info/top_level.txt
balmung-0.0.0.dist-info/RECORD
